wagtail_rss_feed_block/__init__.py
wagtail_rss_feed_block/apps.py
wagtail_rss_feed_block/blocks.py
wagtail_rss_feed_block/templates/wagtail_rss_feed_block/blocks/rss_feed_block.html
wagtail_rss_feed_block/templatetags/rss_feed_tags.py
wagtail_rss_feed_block-0.1.0.dist-info/LICENSE
wagtail_rss_feed_block-0.1.0.dist-info/METADATA
wagtail_rss_feed_block-0.1.0.dist-info/WHEEL
wagtail_rss_feed_block-0.1.0.dist-info/top_level.txt
wagtail_rss_feed_block-0.1.0.dist-info/RECORD
