Metadata-Version: 2.1
Name: wagtail-rss-feed-block
Version: 0.1.0
Summary: Content block displaying RSS feed for Wagtail CMS
Author-email: "LESPROJEKT-SLUŽBY s.r.o." <support@hub4everybody.com>
Project-URL: Homepage, https://github.com/LESPROJEKT/wagtail-rss-feed-block
Project-URL: Bug Tracker, https://github.com/LESPROJEKT/wagtail-rss-feed-block/issues
Classifier: Programming Language :: Python :: 3
Classifier: Intended Audience :: Developers
Classifier: Operating System :: OS Independent
Requires-Python: >=3.7
License-File: LICENSE
Requires-Dist: bleach
Requires-Dist: feedparser
Requires-Dist: wagtail >=4.2.4
